labels_local/labels_local.py
labels_local/labels_local_constants.py
labels_local-0.0.2.dist-info/METADATA
labels_local-0.0.2.dist-info/WHEEL
labels_local-0.0.2.dist-info/top_level.txt
labels_local-0.0.2.dist-info/RECORD
